Metadata-Version: 2.1
Name: soda-core-mysql
Version: 3.5.6
License-File: LICENSE
Requires-Dist: soda-core==3.5.6
Requires-Dist: mysql-connector-python==8.0.30
